CHANGELOG.rst
CONTRIBUTING.rst
LICENSE
MANIFEST.in
README.rst
requirements-dev.txt
requirements.txt
setup.py
tox.ini
ovhcli/__init__.py
ovhcli/cli.py
ovhcli/command.py
ovhcli/context.py
ovhcli/decorators.py
ovhcli/output.py
ovhcli/settings.py
ovhcli.egg-info/PKG-INFO
ovhcli.egg-info/SOURCES.txt
ovhcli.egg-info/dependency_links.txt
ovhcli.egg-info/entry_points.txt
ovhcli.egg-info/requires.txt
ovhcli.egg-info/top_level.txt
ovhcli/modules/__init__.py
ovhcli/modules/me/__init__.py
ovhcli/modules/me/commands.py
ovhcli/modules/me/controllers.py
ovhcli/modules/me/utils.py
ovhcli/modules/setup/__init__.py
ovhcli/modules/setup/commands.py
ovhcli/modules/setup/controllers.py
ovhcli/modules/setup/utils.py
ovhcli/modules/webhosting/__init__.py
ovhcli/modules/webhosting/commands.py
ovhcli/modules/webhosting/controllers.py
ovhcli/modules/webhosting/utils.py
tests/__init__.py
tests/base.py
tests/commands/__init__.py
tests/commands/test_me.py
tests/commands/test_webhosting.py